distributions/Binomialdistribution.py
distributions/Gaussiandistribution.py
distributions/Generaldistribution.py
distributions/__init__.py
sydist-0.1.dist-info/METADATA
sydist-0.1.dist-info/WHEEL
sydist-0.1.dist-info/top_level.txt
sydist-0.1.dist-info/RECORD
