Metadata-Version: 2.1
Name: sydist
Version: 0.1
Summary: Gaussian and Binomial Distribution
Home-page: UNKNOWN
Author: UNKNOWN
Author-email: UNKNOWN
License: UNKNOWN
Platform: UNKNOWN
